ally_ai_chroma/Chroma.py
ally_ai_chroma/__init__.py
ally_ai_chroma-0.5.0.dist-info/LICENSE
ally_ai_chroma-0.5.0.dist-info/METADATA
ally_ai_chroma-0.5.0.dist-info/WHEEL
ally_ai_chroma-0.5.0.dist-info/top_level.txt
ally_ai_chroma-0.5.0.dist-info/RECORD
